[
  {
    "id": "31DAF4",
    "type": "Впишите правильный ответ.",
    "text": "\n        На рисунке приведён график зависимости силы тока от времени в электрической цепи, содержащей катушку, индуктивность которой равна 1 мГн. Определите модуль ЭДС самоиндукции в интервале от 0 до 5 с.         \n\n\nмкВ \n\n\n",
    "image": "https://ege.fipi.ru/docs/BA1F39653304A5B041B656915DC36B38/questions/75212478BBF5940C47D4E8E12A9103CE(copy2)/xs3qstsrc75212478BBF5940C47D4E8E12A9103CE_1_1579853655.png",
    "topic": "3.4.6 Индуктивность. Самоиндукция. ЭДС самоиндукции",
    "page": 3
  },
  {
    "id": "DB72A1",
    "type": "Впишите правильный ответ.",
    "text": "\n Сила тока в катушке с индуктивностью 0,2 Гн за 0,05 с равномерно увеличилась от 2 А до 5 А. Чему равен модуль ЭДС самоиндукции  в катушке? \n\n\nВ \n\n\n",
    "image": null,
    "topic": "3.4.6 Индуктивность. Самоиндукция. ЭДС самоиндукции",
    "page": 14
  },
  {
    "id": "AA47E7",
    "type": "Впишите правильный ответ.",
    "text": "\n        На рисунке приведён график зависимости силы тока I от времени t в катушке, индуктивность которой 1 мГн. Определите модуль ЭДС самоиндукции в катушке  в интервале времени от 0 до 5 с.     \n\n\nмкВ \n\n\n",
    "image": "https://ege.fipi.ru/docs/BA1F39653304A5B041B656915DC36B38/questions/35BE0F7CCB979B3E46E87EA412D0A695(copy1)/xs3qstsrcA62526421E75BE124F64493E5DCFD6AB_1_1486045368.png",
    "topic": "3.4.6 Индуктивность. Самоиндукция. ЭДС самоиндукции",
    "page": 19
  },
  {
    "id": "B8FD36",
    "type": "Впишите правильный ответ.",
    "text": "\n При равномерном изменении силы тока в катушке на 10 А за 0,02 с в ней возникает ЭДС самоиндукции, равная  200 В. Чему равна индуктивность катушки? \n\n\nГн \n\n\n",
    "image": null,
    "topic": "3.4.6 Индуктивность. Самоиндукция. ЭДС самоиндукции",
    "page": 21
  },
  {
    "id": "159D34",
    "type": "Впишите правильный ответ.",
    "text": "\n В катушке индуктивностью 1 мГн сила тока в течение 0,1 с равномерно возрастает от 0 до некоторого конечного значения. При этом в катушке наблюдается ЭДС самоиндукции, модуль которой равен 0,2 В. Определите конечное значение силы тока в катушке. \n\n\nА \n\n\n",
    "image": null,
    "topic": "3.4.6 Индуктивность. Самоиндукция. ЭДС самоиндукции",
    "page": 22
  },
  {
    "id": "A72A3C",
    "type": "Впишите правильный ответ.",
    "text": "\n        На рисунке приведён график зависимости силы тока I от времени t в катушке, индуктивность которой 1 мГн. Определите модуль ЭДС самоиндукции в катушке  в интервале времени от 15 до 20 с.     \n\n\nмкВ \n\n\n",
    "image": "https://ege.fipi.ru/docs/BA1F39653304A5B041B656915DC36B38/questions/06C90A47A6D6BE2444BB3BA586C807B0(copy1)/xs3qstsrc8719020A532E8CDE4881C30173F581E7_1_1486045591.png",
    "topic": "3.4.6 Индуктивность. Самоиндукция. ЭДС самоиндукции",
    "page": 22
  },
  {
    "id": "0C5C8C",
    "type": "Впишите правильный ответ.",
    "text": "\n        На рисунке приведён график зависимости силы тока I в катушке от времени t. Индуктивность катушки равна 0,8 Гн. Определите модуль ЭДС самоиндукции  в промежутке времени от 1 до 5 с.           \n\n\nВ \n\n\n",
    "image": "https://ege.fipi.ru/docs/BA1F39653304A5B041B656915DC36B38/questions/98B11FB0C17B968C49EFCB859A83153E(copy1)/xs3qstsrc98B11FB0C17B968C49EFCB859A83153E_1_1607673721.png",
    "topic": "3.4.6 Индуктивность. Самоиндукция. ЭДС самоиндукции",
    "page": 23
  },
  {
    "id": "C22D32",
    "type": "Выберите один или несколько правильных ответов.",
    "text": "\n        Катушка индуктивности подключена к источнику тока с пренебрежимо малым внутренним сопротивлением через резистор    R=60    Ом (см. рисунок). В момент    t=0    ключ К замыкают. Значения силы тока в цепи, измеренные в последовательные моменты времени  с точностью 0,01 А, представлены в таблице. Сопротивление проводов и катушки пренебрежимо малó.      t, c   0   0,5   1,0   1,5   2,0   3,0   4,0   5,0   6,0     I, A   0   0,12   0,19   0,23   0,26   0,28   0,29   0,30   0,30      Выберите два верных утверждения о процессах, происходящих в цепи. \n\n\n 1)  Напряжение на катушке максимально в момент времени t = 3,0 c.  2)  Энергия катушки минимальна в момент времени  t = 6,0 c.  3)  ЭДС источника тока равна 20 В.  4)  Напряжение на резисторе в момент времени t = 5,0 c равно 18 В.  5)  Модуль ЭДС самоиндукции катушки в момент времени t = 0 равен 18 В. \n\n\n",
    "image": "https://ege.fipi.ru/docs/BA1F39653304A5B041B656915DC36B38/questions/120D3F80C4C18DEC4922C70CD882FF8A(copy1)/xs3qstsrc120D3F80C4C18DEC4922C70CD882FF8A_1_1592383123.png",
    "topic": "3.4.6 Индуктивность. Самоиндукция. ЭДС самоиндукции",
    "page": 34
  }
]